mkdocs_video/__init__.py
mkdocs_video/plugin.py
mkdocs_video-1.5.0.dist-info/LICENSE
mkdocs_video-1.5.0.dist-info/METADATA
mkdocs_video-1.5.0.dist-info/WHEEL
mkdocs_video-1.5.0.dist-info/entry_points.txt
mkdocs_video-1.5.0.dist-info/top_level.txt
mkdocs_video-1.5.0.dist-info/RECORD
