Metadata-Version: 2.1
Name: mkdocs-video
Version: 1.5.0
Home-page: https://github.com/soulless-viewer/mkdocs-video
Author: Mikalai Lisitsa
Author-email: mikalai.lisitsa@gmail.com
License: MIT
Requires-Python: >=3.6
License-File: LICENSE
